{
  "id": "dark",
  "name": "Dark",
  "type": "dark",
  "ui": {
    "accent": "#80CBC4",
    "bgOutermost": "#263238", 
    "fgOutermost": "#546e7a",
    "bgOuter": "#263238",
    "fgOuter": "#546e7a",
    "bgMiddle": "#2d3b41",
    "fgMiddle": "#7695a3",
    "bgInner": "#263238",
    "fgInner": "#37474F",
    "bg": "#263238",
    "fg": "#c4dde1",
    "widgetBorder": "#FFFFFF10",
    "caret": "#FFCC00",
    "scrollbars": "#00000030",
    "scrollbarsHover": "#00000020",
    "tabActiveForeground": "#FFFFFF",
    "lineHighlight": "#000000",
    "indentGuide": "#37474F80",
    "innerBorder": "#37474F80",
    "shadow": "#212c31"
  },
  "scheme": {
    "class": "#FFCB6B",
    "function": "#6abbd9",
    "keyword": "#C792EA",
    "string": "#C3E88D",
    "comment": "#546E7A",
    "operator": "#80CBC4",
    "punctuations": "#808889",
    "jsonOdd": "#32a198",
    "jsonEven": "#2e8ccf",
    "base": {
      "white": "#ffffff",
      "black": "#000000",
      "red": "#FF5370",
      "orange": "#F78C6C",
      "yellow": "#FFCB6B",
      "green": "#C3E88D",
      "cyan": "#89DDFF",
      "blue": "#82AAFF",
      "paleblue": "#B2CCD6",
      "purple": "#C792EA",
      "brown": "#C17E70",
      "pink": "#f07178"
    }
  }
}
